{
	"configurations" : 
	[
		{
			"directories" : 
			[
				{
					"build" : ".",
					"hasInstallRule" : true,
					"jsonFile" : "directory-.-ae5e79406db3c50a2141.json",
					"minimumCMakeVersion" : 
					{
						"string" : "3.12"
					},
					"projectIndex" : 0,
					"source" : ".",
					"targetIndexes" : 
					[
						0,
						1,
						2
					]
				}
			],
			"name" : "",
			"projects" : 
			[
				{
					"directoryIndexes" : 
					[
						0
					],
					"name" : "px4controller",
					"targetIndexes" : 
					[
						0,
						1,
						2
					]
				}
			],
			"targets" : 
			[
				{
					"directoryIndex" : 0,
					"id" : "px4_controller::@6890427a1f51a3e7e1df",
					"jsonFile" : "target-px4_controller-6239440f1cf1ffa100d4.json",
					"name" : "px4_controller",
					"projectIndex" : 0
				},
				{
					"directoryIndex" : 0,
					"id" : "px4controller_uninstall::@6890427a1f51a3e7e1df",
					"jsonFile" : "target-px4controller_uninstall-3ec4aa00c86ca732fe7c.json",
					"name" : "px4controller_uninstall",
					"projectIndex" : 0
				},
				{
					"directoryIndex" : 0,
					"id" : "uninstall::@6890427a1f51a3e7e1df",
					"jsonFile" : "target-uninstall-2af8b25f41f2d6b1b514.json",
					"name" : "uninstall",
					"projectIndex" : 0
				}
			]
		}
	],
	"kind" : "codemodel",
	"paths" : 
	{
		"build" : "/root/px4controller/src/px4controller/build/px4controller",
		"source" : "/root/px4controller/src/px4controller"
	},
	"version" : 
	{
		"major" : 2,
		"minor" : 3
	}
}
